MANIFEST.in
README.md
setup.py
FigSync/README.md
FigSync/__init__.py
FigSync/git.py
FigSync/interactive.py
FigSync/license.txt
FigSync/monitor.py
FigSync/resources.py
FigSync/setup.cfg
FigSync.egg-info/PKG-INFO
FigSync.egg-info/SOURCES.txt
FigSync.egg-info/dependency_links.txt
FigSync.egg-info/not-zip-safe
FigSync.egg-info/requires.txt
FigSync.egg-info/top_level.txt
FigSync/__pycache__/__init__.cpython-312.pyc
FigSync/__pycache__/git.cpython-312.pyc
FigSync/__pycache__/monitor.cpython-312.pyc