Metadata-Version: 2.1
Name: FigSync
Version: 0.0.7
Author: author
Author-email: germanespinosa@gmail.com
License: MIT
Requires-Dist: watchdog
Requires-Dist: pymupdf
